testrunner/__init__.py
testrunner/py.typed
testrunner/runner.py
testrunner/runners/__init__.py
testrunner/runners/abstract_runner.py
testrunner/runners/nose2_runner.py
testrunner/runners/nose_runner.py
testrunner/runners/pytest_runner.py
testrunner/runners/setup_py_runner.py
testrunner/runners/tox_runner.py
test_runner-0.7.0.dist-info/LICENSE.txt
test_runner-0.7.0.dist-info/WHEEL
test_runner-0.7.0.dist-info/METADATA
test_runner-0.7.0.dist-info/RECORD
