Metadata-Version: 2.1
Name: test-runner
Version: 0.7.0
Summary: A small test runner library for Python testing
Home-page: https://github.com/pytesting/test-runner
License: LGPL-3.0+
Keywords: test runner,unittest,nose,pytest
Author: Stephan Lukasczyk
Author-email: python-test-runner@googlegroups.com
Requires-Python: >=3.6,<4.0
Classifier: Development Status :: 3 - Alpha
Classifier: Intended Audience :: Developers
Classifier: Intended Audience :: Education
Classifier: Intended Audience :: Science/Research
Classifier: License :: OSI Approved :: GNU Lesser General Public License v3 or later (LGPLv3+)
Classifier: Operating System :: POSIX :: Linux
Classifier: Programming Language :: Python
Classifier: Programming Language :: Python :: 3
Classifier: Programming Language :: Python :: 3 :: Only
Classifier: Programming Language :: Python :: 3.6
Classifier: Programming Language :: Python :: 3.7
Classifier: Programming Language :: Python :: 3.8
Classifier: Topic :: Education
Classifier: Topic :: Education :: Testing
Classifier: Topic :: Software Development
Classifier: Topic :: Software Development :: Testing
Classifier: Topic :: Software Development :: Testing :: Unit
Classifier: Topic :: Utilities
Requires-Dist: attr (>=0.3.1,<0.4.0)
Requires-Dist: benchexec (>=2.5,<3.0)
Requires-Dist: deprecated (>=1.2,<2.0)
Requires-Dist: pipfile (>=0.0.2,<0.0.3)
Requires-Dist: plumbum (>=1.6,<2.0)
Requires-Dist: pytesting-utils (>=0.5.0,<0.6.0)
Requires-Dist: virtualenv (>=16.7,<17.0)
Project-URL: Repository, https://github.com/pytesting/test-runner
